MANIFEST.in
requirements.txt
setup.cfg
setup.py
apcaccess/__init__.py
apcaccess/__main__.py
apcaccess/status.py
apcaccess.egg-info/PKG-INFO
apcaccess.egg-info/SOURCES.txt
apcaccess.egg-info/dependency_links.txt
apcaccess.egg-info/entry_points.txt
apcaccess.egg-info/not-zip-safe
apcaccess.egg-info/top_level.txt