Metadata-Version: 1.1
Name: apcaccess
Version: 0.0.10
Summary: This project implements the apcaccess tool in pure Python and provides
Home-page: https://github.com/flyte/apcaccess
Author: Ellis Percival
Author-email: apcaccess@failcode.co.uk
License: MIT
Platform: UNKNOWN
Classifier: Programming Language :: Python
Classifier: Intended Audience :: Developers
Classifier: License :: OSI Approved :: MIT License
Classifier: Natural Language :: English
Classifier: Operating System :: OS Independent
Classifier: Topic :: Communications
Classifier: Topic :: Home Automation
Classifier: Topic :: System :: Networking
